.gitignore
AUTHORS.rst
CONTRIBUTING.rst
HISTORY.rst
LICENSE
README.rst
docs/_static/impeachment-statements.svg
docs/_static/textnets-logo.svg
docs/advanced.rst
docs/authors.rst
docs/bibliography.rst
docs/conf.py
docs/contributing.rst
docs/history.rst
docs/index.rst
docs/installation.rst
docs/license.rst
docs/reference.rst
docs/refs.bib
docs/textnets-logo-sm.svg
docs/tutorial.rst
tests/__init__.py
tests/conftest.py
tests/test_textnets.py
textnets-0.10.4.dist-info/METADATA
textnets-0.10.4.dist-info/WHEEL
textnets-0.10.4.dist-info/entry_points.txt
textnets-0.10.4.dist-info/licenses/LICENSE
textnets/__init__.py
textnets/_ext.c
textnets/_ext.cp311-win_amd64.pyd
textnets/_ext.pxd
textnets/_ext.pyx
textnets/_util.py
textnets/config.py
textnets/corpus.py
textnets/examples.py
textnets/network.py
textnets/viz.py
textnets-0.10.4.dist-info/RECORD
