Metadata-Version: 2.1
Name: textnets
Version: 0.10.4
Summary: Automated text analysis with networks
Keywords: computational social science,network analysis,nlp,text analysis,visualization
Author-Email: "John D. Boy" <jboy@bius.moe>
License: GPL-3.0-only
Classifier: Development Status :: 4 - Beta
Classifier: Intended Audience :: Science/Research
Classifier: Operating System :: OS Independent
Classifier: Natural Language :: English
Classifier: Programming Language :: Cython
Classifier: Programming Language :: Python
Classifier: Programming Language :: Python :: 3
Classifier: Programming Language :: Python :: 3 :: Only
Classifier: Programming Language :: Python :: 3.10
Classifier: Programming Language :: Python :: 3.11
Classifier: Programming Language :: Python :: 3.12
Classifier: Programming Language :: Python :: 3.13
Classifier: Topic :: Scientific/Engineering :: Visualization
Classifier: Topic :: Sociology
Project-URL: Bug Tracker, https://github.com/jboynyc/textnets/issues
Project-URL: Changelog, https://textnets.readthedocs.io/en/stable/history.html
Project-URL: Documentation, https://textnets.readthedocs.io
Project-URL: homepage, https://textnets.readthedocs.io
Project-URL: repository, https://github.com/jboynyc/textnets
Requires-Python: <3.14,>=3.10
Requires-Dist: igraph
Requires-Dist: leidenalg
Requires-Dist: pandas<3.0.0,>=2.2.3
Requires-Dist: scipy<2.0.0,>=1.14.1
Requires-Dist: spacy<4.0.0,>=3.8.5
Requires-Dist: spacy-lookups-data<2.0.0,>=1.0.5
Requires-Dist: toolz<1.0.0,>=0.12.1
Requires-Dist: tqdm<5.0.0,>=4.66.5
Requires-Dist: wasabi<2.0.0,>=1.1.3
Requires-Dist: pyarrow>=20.0.0; implementation_name != "pypy"
Requires-Dist: matplotlib<4.0.0,>=3.10.1
Provides-Extra: zh
Requires-Dist: jieba<1.0.0,>=0.42.1; extra == "zh"
Provides-Extra: cjk
Requires-Dist: mpl-font==1.1.0; extra == "cjk"
